taskhive/__init__.py
taskhive/progress_callbacks.py
taskhive/taskhive.py
taskhive/utils.py
taskhive/workers.py
taskhive-1.0.2.dist-info/METADATA
taskhive-1.0.2.dist-info/WHEEL
taskhive-1.0.2.dist-info/top_level.txt
taskhive-1.0.2.dist-info/RECORD
