Metadata-Version: 2.1
Name: taskhive
Version: 1.0.2
Summary: A library for paralleling the execution of functions in python
Author: Akshit Sharma
Author-email: akshitsharma@mines.edu
Requires-Dist: tqdm
Requires-Dist: yaspin
